{
"No.":"21","Age":"24",
"Sex":"Male",
"Education":"Master's degree",
"Vis-Exp":"1 to 3 years",
"Data-Exp":"3 to 5 years",
"QA":[
{"Set_No":"1","T_No":"1","time":"20.408","index":"05_T3_L_1k","CorrectA":"2","PersonA":"3","correctness":0},
{"Set_No":"1","T_No":"2","time":"7.772","index":"29_T1_H_1k","CorrectA":"1","PersonA":"1","correctness":1},
{"Set_No":"1","T_No":"3","time":"8.61","index":"23_T3_H_100","CorrectA":"1","PersonA":"1","correctness":1},
{"Set_No":"1","T_No":"4","time":"8.482","index":"25_T3_L_100","CorrectA":"2","PersonA":"2","correctness":1},
{"Set_No":"1","T_No":"5","time":"16.697","index":"23_T1_M_1k","CorrectA":"2","PersonA":"2","correctness":1},
{"Set_No":"1","T_No":"6","time":"13.873","index":"24_T1_L_100","CorrectA":"2","PersonA":"2","correctness":1},
{"Set_No":"1","T_No":"7","time":"5.919","index":"04_T2_M_300","CorrectA":"1","PersonA":"3","correctness":0},
{"Set_No":"1","T_No":"8","time":"12.73","index":"26_T1_M_300","CorrectA":"1","PersonA":"1","correctness":1},
{"Set_No":"1","T_No":"9","time":"20.893","index":"20_T3_H_100","CorrectA":"2","PersonA":"3","correctness":0},
{"Set_No":"1","T_No":"10","time":"14.724","index":"02_T3_M_100","CorrectA":"3","PersonA":"3","correctness":1},
{"Set_No":"1","T_No":"11","time":"7.442","index":"17_T1_H_1k","CorrectA":"1","PersonA":"1","correctness":1},
{"Set_No":"1","T_No":"12","time":"11.057","index":"05_T1_H_300","CorrectA":"3","PersonA":"3","correctness":1},
{"Set_No":"1","T_No":"13","time":"9.318","index":"02_T2_H_300","CorrectA":"1","PersonA":"1","correctness":1},
{"Set_No":"1","T_No":"14","time":"12.829","index":"30_T3_L_300","CorrectA":"2","PersonA":"2","correctness":1},
{"Set_No":"1","T_No":"15","time":"9.729","index":"25_T2_M_300","CorrectA":"1","PersonA":"1","correctness":1},
{"Set_No":"2","T_No":"1","time":"7.648","index":"07_T2_H_1k","CorrectA":"1","PersonA":"1","correctness":1},
{"Set_No":"2","T_No":"2","time":"3.844","index":"26_T2_L_100","CorrectA":"3","PersonA":"3","correctness":1},
{"Set_No":"2","T_No":"3","time":"5.962","index":"28_T1_M_100","CorrectA":"3","PersonA":"3","correctness":1},
{"Set_No":"2","T_No":"4","time":"3.597","index":"03_T1_H_100","CorrectA":"1","PersonA":"1","correctness":1},
{"Set_No":"2","T_No":"5","time":"33.73","index":"26_T3_H_1k","CorrectA":"2","PersonA":"3","correctness":0},
{"Set_No":"2","T_No":"6","time":"6.245","index":"07_T3_M_300","CorrectA":"1","PersonA":"1","correctness":1},
{"Set_No":"2","T_No":"7","time":"4.177","index":"02_T1_L_1k","CorrectA":"3","PersonA":"3","correctness":1},
{"Set_No":"2","T_No":"8","time":"5.832","index":"05_T2_M_100","CorrectA":"2","PersonA":"3","correctness":0},
{"Set_No":"2","T_No":"9","time":"5.24","index":"24_T2_H_1k","CorrectA":"1","PersonA":"1","correctness":1},
{"Set_No":"2","T_No":"10","time":"20.482","index":"04_T3_L_100","CorrectA":"1","PersonA":"3","correctness":0},
{"Set_No":"2","T_No":"11","time":"5.333","index":"30_T1_H_100","CorrectA":"1","PersonA":"3","correctness":0},
{"Set_No":"2","T_No":"12","time":"10.921","index":"23_T2_L_300","CorrectA":"3","PersonA":"1","correctness":0},
{"Set_No":"2","T_No":"13","time":"10.572","index":"29_T3_L_100","CorrectA":"1","PersonA":"2","correctness":0},
{"Set_No":"2","T_No":"14","time":"7.265","index":"24_T3_M_300","CorrectA":"1","PersonA":"1","correctness":1},
{"Set_No":"2","T_No":"15","time":"11.557","index":"07_T1_L_100","CorrectA":"2","PersonA":"2","correctness":1},
{"Set_No":"3","T_No":"1","time":"16.991","index":"06_T3_L_1k","CorrectA":"1","PersonA":"1","correctness":1},
{"Set_No":"3","T_No":"2","time":"6.78","index":"20_T1_M_1k","CorrectA":"1","PersonA":"1","correctness":1},
{"Set_No":"3","T_No":"3","time":"2.924","index":"04_T1_H_1k","CorrectA":"2","PersonA":"2","correctness":1},
{"Set_No":"3","T_No":"4","time":"5.251","index":"17_T3_L_100","CorrectA":"2","PersonA":"2","correctness":1},
{"Set_No":"3","T_No":"5","time":"4.775","index":"20_T2_L_300","CorrectA":"3","PersonA":"2","correctness":0},
{"Set_No":"3","T_No":"6","time":"6.165","index":"06_T1_H_300","CorrectA":"1","PersonA":"1","correctness":1},
{"Set_No":"3","T_No":"7","time":"3.346","index":"25_T1_H_1k","CorrectA":"1","PersonA":"1","correctness":1},
{"Set_No":"3","T_No":"8","time":"8.847","index":"29_T2_M_300","CorrectA":"1","PersonA":"1","correctness":1},
{"Set_No":"3","T_No":"9","time":"8.131","index":"03_T3_L_300","CorrectA":"3","PersonA":"3","correctness":1},
{"Set_No":"3","T_No":"10","time":"5.521","index":"30_T2_M_1k","CorrectA":"2","PersonA":"2","correctness":1},
{"Set_No":"3","T_No":"11","time":"8.167","index":"06_T2_M_100","CorrectA":"1","PersonA":"1","correctness":1},
{"Set_No":"3","T_No":"12","time":"2.92","index":"17_T2_M_300","CorrectA":"1","PersonA":"1","correctness":1},
{"Set_No":"3","T_No":"13","time":"4.77","index":"28_T2_L_1k","CorrectA":"3","PersonA":"3","correctness":1},
{"Set_No":"3","T_No":"14","time":"7.92","index":"28_T3_H_300","CorrectA":"2","PersonA":"3","correctness":0},
{"Set_No":"3","T_No":"15","time":"5.837","index":"03_T2_M_1k","CorrectA":"1","PersonA":"1","correctness":1}],
"browser":"(1200,800)",
"feedback_T1":"9",
"feedback_T2":"1",
"feedback_T3":"1",
"vcode":"59tFq5"}